[
  {
    "id": "och0qibbnjv",
    "name": "特定商取引法に基づく表記",
    "price": "×",
    "category": null
  },
  {
    "id": "yfwg-nzy1",
    "name": "特定対応ケージ！　Goisu～な新店【Exotic Reptiles Shop『Goisu〜』】",
    "price": "×",
    "category": null
  },
  {
    "id": "vh4fde4_8gk",
    "name": "【重要】保証期間・仕様書で取り決める内容について",
    "price": "×",
    "category": null
  },
  {
    "id": "4f65y0p984g8",
    "name": "【オプション紹介】スチールラック連結ブラケット　地震対策",
    "price": "×",
    "category": null
  },
  {
    "id": "15j097521w1",
    "name": "【ご購入の流れとお支払方法】",
    "price": "×",
    "category": null
  },
  {
    "id": "19st1io_0ijf",
    "name": "チップ系床材をお使いの方への提案（チップのこぼれ防止構造）",
    "price": "×",
    "category": null
  },
  {
    "id": "jzlogho_z",
    "name": "ケージ持ち上げ用ハンドル　ステンレス製",
    "price": "×",
    "category": null
  },
  {
    "id": "yv74qdvvd1",
    "name": "アクリルパネルの色変更（側面・背面・床面）",
    "price": "×",
    "category": null
  },
  {
    "id": "cr555d8hm4",
    "name": "給水器",
    "price": "×",
    "category": null
  },
  {
    "id": "9vc658jwgsn",
    "name": "小さなハウス",
    "price": "×",
    "category": null
  },
  {
    "id": "805a3tumwcyi",
    "name": "災害時の対処方法",
    "price": "×",
    "category": null
  },
  {
    "id": "z4emq74rdvg",
    "name": "メタルサイレント32下パン",
    "price": "×",
    "category": null
  },
  {
    "id": "a-u19jnitv",
    "name": "オプション品紹介　床材にソイルや砂をご利用の方向け",
    "price": "×",
    "category": null
  },
  {
    "id": "e25n-sq63b",
    "name": "〇紹介　TypeH　ご購入されたお客様へ。引き出し不意開防止・ロック板取付方法",
    "price": "×",
    "category": null
  },
  {
    "id": "ar7xpey517hh",
    "name": "2室分け天板上乗せ仕切り取外し方法",
    "price": "×",
    "category": null
  },
  {
    "id": "0alcg3jeac0",
    "name": "●価格表　TypeA全面スライド扉",
    "price": "×",
    "category": null
  },
  {
    "id": "185s00okm5g4",
    "name": "●価格表　TypeB全面スライド扉（2室分け）",
    "price": "×",
    "category": null
  },
  {
    "id": "1pl1n85fsz",
    "name": "●価格表　TypeC前窓付きスライド扉",
    "price": "×",
    "category": null
  },
  {
    "id": "o4oic_1m15",
    "name": "●価格表　TypeD前窓付きスライド扉（２室分け）",
    "price": "×",
    "category": null
  },
  {
    "id": "ds7g4cria7",
    "name": "●価格表　TypeF2M フクロモモンガ向け　前開き扉　引き出しなし",
    "price": "×",
    "category": null
  },
  {
    "id": "1d-s8t2qe-u",
    "name": "●価格表　TypeFM フクロモモンガ向け　前開き扉　引き出し付き",
    "price": "×",
    "category": null
  },
  {
    "id": "ehnlroanvvp",
    "name": "●価格表　TypeAF フクロモモンガ専用　スライド扉式正面扉",
    "price": "×",
    "category": null
  },
  {
    "id": "hbsjx2w90",
    "name": "●価格表　TypeF2 フクロモモンガ向け　オカモチ式正面扉　引き出しなし",
    "price": "×",
    "category": null
  },
  {
    "id": "qxs8gru082g",
    "name": "●価格表　TypeF フクロモモンガ向け　オカモチ式正面扉　引き出し付き",
    "price": "×",
    "category": null
  }
]